dayu_widgets_overlay2/__init__.py
dayu_widgets_overlay2/__version__.py
dayu_widgets_overlay2/overlay.py
dayu_widgets_overlay2-0.1.2.dist-info/LICENSE
dayu_widgets_overlay2-0.1.2.dist-info/METADATA
dayu_widgets_overlay2-0.1.2.dist-info/WHEEL
dayu_widgets_overlay2-0.1.2.dist-info/RECORD
